cli.py
pushover.py
softxperience_pushover-1.0.dist-info/AUTHORS.rst
softxperience_pushover-1.0.dist-info/LICENSE
softxperience_pushover-1.0.dist-info/METADATA
softxperience_pushover-1.0.dist-info/WHEEL
softxperience_pushover-1.0.dist-info/entry_points.txt
softxperience_pushover-1.0.dist-info/top_level.txt
softxperience_pushover-1.0.dist-info/RECORD
