Metadata-Version: 2.1
Name: softxperience-pushover
Version: 1.0
Summary: Comprehensive bindings and command line utility for the Pushover notification service
Home-page: https://github.com/SoftXperience/python-pushover
Author: Marcus Terasa
Author-email: info@softxperience.com
License: GNU GPLv3
Platform: UNKNOWN
Requires-Dist: requests (>=1.0)
